samslacker/__init__.py
samslacker/api_requestor.py
samslacker/resources.py
samslacker/version.py
samslacker_python-0.0.6.6.dist-info/LICENSE
samslacker_python-0.0.6.6.dist-info/METADATA
samslacker_python-0.0.6.6.dist-info/WHEEL
samslacker_python-0.0.6.6.dist-info/top_level.txt
samslacker_python-0.0.6.6.dist-info/RECORD
