Metadata-Version: 2.1
Name: samslacker-python
Version: 0.0.6.6
Summary: Python wrapper for Sam Slacker API
Home-page: https://samplify.io
Author: Fire In Belly Limited
Author-email: developers@samplify.io
License: MIT
Platform: UNKNOWN
Requires-Dist: requests
Requires-Dist: boto3
